eddymotion/__init__.py
eddymotion/__main__.py
eddymotion/_version.py
eddymotion/estimator.py
eddymotion/utils.py
eddymotion/viz.py
eddymotion/cli/__init__.py
eddymotion/cli/parser.py
eddymotion/cli/run.py
eddymotion/config/dwi-to-b0_level0.json
eddymotion/config/dwi-to-dwi_level0.json
eddymotion/config/dwi-to-dwi_level1.json
eddymotion/data/__init__.py
eddymotion/data/dmri.py
eddymotion/data/pet.py
eddymotion/data/splitting.py
eddymotion/data/utils.py
eddymotion/model/__init__.py
eddymotion/model/base.py
eddymotion-0.1.15.dist-info/METADATA
eddymotion-0.1.15.dist-info/WHEEL
eddymotion-0.1.15.dist-info/entry_points.txt
eddymotion-0.1.15.dist-info/licenses/LICENSE
eddymotion-0.1.15.dist-info/RECORD
