Metadata-Version: 2.3
Name: eddymotion
Version: 0.1.15
Summary: Pure python eddy-current and head-motion correction for dMRI, an extension of QSIprep's SHOREline algorithm (Cieslak, 2020) to multiple diffusion models.
Project-URL: Documentation, https://www.nipreps.org/eddymotion
Project-URL: Home, https://github.com/nipreps/eddymotion
Project-URL: NiPreps, https://www.nipreps.org/
Author-email: The NiPreps Developers <nipreps@gmail.com>
License-Expression: Apache-2.0
License-File: LICENSE
Classifier: Development Status :: 3 - Alpha
Classifier: Intended Audience :: Science/Research
Classifier: License :: OSI Approved :: Apache Software License
Classifier: Programming Language :: Python :: 3.10
Classifier: Programming Language :: Python :: 3.11
Classifier: Programming Language :: Python :: 3.12
Classifier: Topic :: Scientific/Engineering :: Image Recognition
Requires-Python: >=3.10
Requires-Dist: dipy>=1.3.0
Requires-Dist: joblib
Requires-Dist: nest-asyncio>=1.5.1
Requires-Dist: nipype<2.0,>=1.5.1
Requires-Dist: nireports
Requires-Dist: nitransforms>=21.0.0
Requires-Dist: numpy>=1.17.3
Requires-Dist: scikit-image>=0.14.2
Requires-Dist: scipy>=1.8.0
Provides-Extra: all
Requires-Dist: attrs>=20.1.0; extra == 'all'
Requires-Dist: coverage; extra == 'all'
Requires-Dist: furo>=2024.01.29; extra == 'all'
Requires-Dist: matplotlib>=2.2.0; extra == 'all'
Requires-Dist: nbsphinx; extra == 'all'
Requires-Dist: nilearn; extra == 'all'
Requires-Dist: packaging; extra == 'all'
Requires-Dist: popylar>=0.2; extra == 'all'
Requires-Dist: pre-commit; extra == 'all'
Requires-Dist: pre-commit-hooks; extra == 'all'
Requires-Dist: psutil>=5.4; extra == 'all'
Requires-Dist: pydot>=1.2.3; extra == 'all'
Requires-Dist: pydotplus; extra == 'all'
Requires-Dist: pytest-cov; extra == 'all'
Requires-Dist: pytest-env; extra == 'all'
Requires-Dist: pytest-xdist>=1.28; extra == 'all'
Requires-Dist: pytest>=4.4; extra == 'all'
Requires-Dist: ruff; extra == 'all'
Requires-Dist: sphinx-argparse; extra == 'all'
Requires-Dist: sphinx-rtd-theme; extra == 'all'
Requires-Dist: sphinx>=4.5; extra == 'all'
Requires-Dist: sphinxcontrib-apidoc~=0.3.0; extra == 'all'
Requires-Dist: sphinxcontrib-napoleon; extra == 'all'
Requires-Dist: sphinxcontrib-versioning; extra == 'all'
Provides-Extra: dev
Requires-Dist: pre-commit; extra == 'dev'
Requires-Dist: pre-commit-hooks; extra == 'dev'
Requires-Dist: ruff; extra == 'dev'
Provides-Extra: doc
Requires-Dist: attrs>=20.1.0; extra == 'doc'
Requires-Dist: furo>=2024.01.29; extra == 'doc'
Requires-Dist: matplotlib>=2.2.0; extra == 'doc'
Requires-Dist: nbsphinx; extra == 'doc'
Requires-Dist: packaging; extra == 'doc'
Requires-Dist: pydot>=1.2.3; extra == 'doc'
Requires-Dist: pydotplus; extra == 'doc'
Requires-Dist: sphinx-argparse; extra == 'doc'
Requires-Dist: sphinx-rtd-theme; extra == 'doc'
Requires-Dist: sphinx>=4.5; extra == 'doc'
Requires-Dist: sphinxcontrib-apidoc~=0.3.0; extra == 'doc'
Requires-Dist: sphinxcontrib-napoleon; extra == 'doc'
Requires-Dist: sphinxcontrib-versioning; extra == 'doc'
Provides-Extra: docs
Requires-Dist: attrs>=20.1.0; extra == 'docs'
Requires-Dist: furo>=2024.01.29; extra == 'docs'
Requires-Dist: matplotlib>=2.2.0; extra == 'docs'
Requires-Dist: nbsphinx; extra == 'docs'
Requires-Dist: packaging; extra == 'docs'
Requires-Dist: pydot>=1.2.3; extra == 'docs'
Requires-Dist: pydotplus; extra == 'docs'
Requires-Dist: sphinx-argparse; extra == 'docs'
Requires-Dist: sphinx-rtd-theme; extra == 'docs'
Requires-Dist: sphinx>=4.5; extra == 'docs'
Requires-Dist: sphinxcontrib-apidoc~=0.3.0; extra == 'docs'
Requires-Dist: sphinxcontrib-napoleon; extra == 'docs'
Requires-Dist: sphinxcontrib-versioning; extra == 'docs'
Provides-Extra: plotting
Requires-Dist: nilearn; extra == 'plotting'
Provides-Extra: popylar
Requires-Dist: popylar>=0.2; extra == 'popylar'
Provides-Extra: resmon
Requires-Dist: psutil>=5.4; extra == 'resmon'
Provides-Extra: test
Requires-Dist: coverage; extra == 'test'
Requires-Dist: pytest-cov; extra == 'test'
Requires-Dist: pytest-env; extra == 'test'
Requires-Dist: pytest-xdist>=1.28; extra == 'test'
Requires-Dist: pytest>=4.4; extra == 'test'
Provides-Extra: tests
Requires-Dist: coverage; extra == 'tests'
Requires-Dist: pytest-cov; extra == 'tests'
Requires-Dist: pytest-env; extra == 'tests'
Requires-Dist: pytest-xdist>=1.28; extra == 'tests'
Requires-Dist: pytest>=4.4; extra == 'tests'
